{
  "hash": "e109abd0a5b9d5fdd7c192f92572a461",
  "result": {
    "markdown": "---\ntitle: \"Laboratory Move\"\ndescription: |\n  A short description of the post.\nauthor:\n  - name: Rodney Dyer\n    url: https://dyerlab.org\n    affiliation: Center for Environmental Studies\n    affiliation_url: https://ces.vcu.edu\n    orcid_id: 0000-0003-4707-3453\ndate: 2015-12-02\noutput:\n  distill::distill_article:\n    self_contained: false\n---\n\n\n\n\n\nThe Dyer laboratory is moving!  I don not know the final destination, but it has been verified that the current space is unusable.  After 31 months of not having a functional laboratory&#8230;\n \n \n \n",
    "supporting": [],
    "filters": [
      "rmarkdown/pagebreak.lua"
    ],
    "includes": {},
    "engineDependencies": {},
    "preserve": {},
    "postProcess": true
  }
}